DataMemory/DataMemory.v
module DataMemory (
    input wire clk,                     // Clock signal
    input wire [31:0] address,          // Address for data memory
    input wire [31:0] writeData,        // Data to write into memory
    input wire memWrite,                // Write enable signal
    input wire memRead,                 // Read enable signal
    output reg [31:0] readData          // Data read from memory
);
    // Data Memory size
    parameter memSize = 1024;
    reg [31:0] dataMem[0:memSize-1];

    // Memory write operation
    always @(posedge clk) begin
        if (memWrite) begin
            dataMem[address[11:2]] <= writeData; // Write data to indexed memory
        end
    end

    // Memory read operation
    always @(*) begin
        if (memRead) begin
            readData = dataMem[address[11:2]]; // Asynchronous read
        end else begin
            readData = 32'b0; // Default value when read is disabled
        end
    end
endmodule

DataMemory/DataMemoryTestBench.v
module DataMemory_tb;
    // Testbench signals
    reg clk;
    reg [31:0] address;
    reg [31:0] writeData;
    reg memWrite, memRead;
    wire [31:0] readData;

    // Instantiate the Data Memory module
    DataMemory uut (
        .clk(clk),
        .address(address),
        .writeData(writeData),
        .memWrite(memWrite),
        .memRead(memRead),
        .readData(readData)
    );

    //clock signal
    initial begin
        clk = 0;
        forever #5 clk = ~clk;
    end

    // Test sequence
    initial begin
        // Open VCD file for GTKWave
        $dumpfile("DataMemory_tb.vcd");
        $dumpvars(0, DataMemory_tb);

        //initialize signals
        address = 0;
        writeData = 0;
        memWrite = 0;
        memRead = 0;

        // Write data to memory at address 0x04
        #10 address = 32'h4; 
        writeData = 32'hDEADBEEF; 
        memWrite = 1;
        #10 memWrite = 0;

        // Read data from memory at address 0x04
        #10 address = 32'h4; 
        memRead = 1;
        #10 memRead = 0;

        // Write data to memory at address 0x08
        #10 address = 32'h8; 
        writeData = 32'h12345678; 
        memWrite = 1;
        #10 memWrite = 0;

        // Read data from memory at address 0x08
        #10 address = 32'h8; 
        memRead = 1;
        #10 memRead = 0;

        // Attempt to read from an uninitialized address
        #10 address = 32'hC; 
        memRead = 1;
        #10 memRead = 0;

        // Monitor signals in the simulation
        $monitor("Time = %0d, Address = %h, WriteData = %h, ReadData = %h", $time, address, writeData, readData);

        // Finish the simulation
        #10 $finish;
    end

endmodule

DataMemory/DataMemory_tb.vcd
$date
	Wed Jan 01 14:00:44 2025
$end
$version
	Icarus Verilog
$end
$timescale
	1s
$end
$scope module DataMemory_tb $end
$var wire 32 ! readData [31:0] $end
$var reg 32 " address [31:0] $end
$var reg 1 # clk $end
$var reg 1 $ memRead $end
$var reg 1 % memWrite $end
$var reg 32 & writeData [31:0] $end
$scope module uut $end
$var wire 32 ' address [31:0] $end
$var wire 1 # clk $end
$var wire 1 $ memRead $end
$var wire 1 % memWrite $end
$var wire 32 ( writeData [31:0] $end
$var parameter 32 ) memSize $end
$var reg 32 * readData [31:0] $end
$upscope $end
$upscope $end
$enddefinitions $end
$comment Show the parameter values. $end
$dumpall
b10000000000 )
$end
#0
$dumpvars
b0 *
b0 (
b0 '
b0 &
0%
0$
0#
b0 "
b0 !
$end
#5
1#
#10
0#
1%
b11011110101011011011111011101111 &
b11011110101011011011111011101111 (
b100 "
b100 '
#15
1#
#20
0#
0%
#25
1#
#30
b11011110101011011011111011101111 !
b11011110101011011011111011101111 *
0#
1$
#35
1#
#40
b0 !
b0 *
0#
0$
#45
1#
#50
0#
1%
b10010001101000101011001111000 &
b10010001101000101011001111000 (
b1000 "
b1000 '
#55
1#
#60
0#
0%
#65
1#
#70
b10010001101000101011001111000 !
b10010001101000101011001111000 *
0#
1$
#75
1#
#80
b0 !
b0 *
0#
0$
#85
1#
#90
bx !
bx *
0#
1$
b1100 "
b1100 '
#95
1#
#100
b0 !
b0 *
0#
0$
