InstructionMemory/InstructionMemory.v
// Instruction Memory module
// Group 06

module INSTRUCTION_MEMORY (
    input wire [31:0] ADDRESS, // Program Counter
    output wire [31:0] INSTRUCTION // Instruction
);

// Instruction Memory size
parameter MEM_SIZE = 1024;
reg [31:0] INSTRUCTIONS_MEM[0:MEM_SIZE-1];

// Initialize the Instruction Memory
initial begin 
    // Load the instructions to memory
    INSTRUCTIONS_MEM[0] <= 32'h00000013; // ADDI x0, x0, 0 (NOP)
    INSTRUCTIONS_MEM[4] <= 32'h00000093; // ADDI x1, x0, 0
    INSTRUCTIONS_MEM[8] <= 32'h00100113; // ADDI x2, x0, 1
    INSTRUCTIONS_MEM[12] <= 32'h002081B3; // ADD x3, x1, x2
    INSTRUCTIONS_MEM[16] <= 32'h00310133; // ADDI x2, x2, 3
    INSTRUCTIONS_MEM[20] <= 32'h4041A183; // SUB x3, x2, x1
end

// Read the Instruction from the Instruction Memory
assign INSTRUCTION = INSTRUCTIONS_MEM[ADDRESS];

endmodule

ProgramCounter/ProgramCounter.v
module PROGRAM_COUNTER (
    input wire CLK,
    input wire RST,
    input wire [31:0] NEXT_PC,
    output reg [31:0] PC,
    output wire [31:0] PC_PLUS4
);

always @(posedge CLK or posedge RST) begin
    if (RST)
        PC <= 32'b0;
    else
        PC <= NEXT_PC;
end

assign PC_PLUS4 = PC + 4;

endmodule

Stages/IF.v
module IF (
    input wire CLK,
    input wire RST,
    input wire [31:0] NEXT_PC,
    output wire [31:0] IF_PC,
    output wire [31:0] IF_PC_PLUS4,
    output wire [31:0] IF_INSTRUCTION
);
    wire [31:0] PC;
    wire [31:0] PC_PLUS4;

    PROGRAM_COUNTER PC_INST (
        .CLK(CLK),
        .RST(RST),
        .NEXT_PC(NEXT_PC),
        .PC(PC),
        .PC_PLUS4(PC_PLUS4)
    );

    assign IF_PC = PC;
    assign IF_PC_PLUS4 = PC_PLUS4;

    // Instruction Memory
    INSTRUCTION_MEMORY instruction_memory (
        .ADDRESS(PC),
        .INSTRUCTION(IF_INSTRUCTION)
    );

endmodule

CPU/IF/IFTestBench.v
module IFTestBench;

    // Testbench signals
    reg CLK;
    reg RST;
    reg [31:0] PCADDRESS; // Program Counter
    wire [31:0] INSTRUCTION; // Instruction output
    wire [31:0] PCPLUS4; // Program Counter + 4
    wire [31:0] IF_PC; // IF module PC output

    // Instantiate the IF module
    IF UUT (
        .CLK(CLK),
        .RST(RST),
        .NEXT_PC(PCADDRESS),
        .IF_PC(IF_PC),
        .IF_PC_PLUS4(PCPLUS4),
        .IF_INSTRUCTION(INSTRUCTION)
    );

    // Clock generation
    initial begin
        CLK = 0;
        forever #5 CLK = ~CLK;
    end

    // Test sequence
    initial begin
        // Open VCD file for GTKWave
        $dumpfile("IFTESTBENCH.vcd");
        $dumpvars(0, IFTestBench);

        // Monitor signals in the simulation
        $monitor("Time = %0d, PC Address = %h, Instruction = %h, PC + 4 = %h", $time, PCADDRESS, INSTRUCTION, PCPLUS4);

        // Initialize signals
        RST = 1;
        PCADDRESS = 0;
        #10;
        RST = 0;

        // Test case 1: Access instruction at address 0
        PCADDRESS = 0;
        #10;

        // Test case 2: Access instruction at address 4
        PCADDRESS = 4;
        #10;

        // Test case 3: Access instruction at address 8
        PCADDRESS = 8;
        #10;

        // Test case 4: Access instruction at address 12
        PCADDRESS = 12;
        #10;

        // Test case 5: Access instruction at address 16
        PCADDRESS = 16;
        #10;

        // Test case 6: Access instruction at address 20
        PCADDRESS = 20;
        #10;

        $finish;
    end
endmodule

// # Navigate to the directory containing your Verilog files
// cd /d:/My projects/e20-co502-RV32IM_Pipelined_Processor_Group-06/CPU/IF/

// # Compile the Verilog files with correct paths
// iverilog -o IFTestBench.vvp IF.v IFTestBench.v ../../ProgramCounter/ProgramCounter.v ../../InstructionMemory/InstructionMemory.v

// # Run the simulation
// vvp IFTestBench.vvp

// # View the waveform using GTKWave (optional)
// gtkwave IFTESTBENCH.vcd

CPU/IF/IFTESTBENCH.vcd
$date
	Wed Jan 15 14:50:48 2025
$end
$version
	Icarus Verilog
$end
$timescale
	1s
$end
$scope module IFTestBench $end
$var wire 32 ! PCPLUS4 [31:0] $end
$var wire 32 " INSTRUCTION [31:0] $end
$var wire 32 # IF_PC [31:0] $end
$var reg 1 $ CLK $end
$var reg 32 % PCADDRESS [31:0] $end
$var reg 1 & RST $end
$scope module UUT $end
$var wire 1 $ CLK $end
$var wire 32 ' IF_PC [31:0] $end
$var wire 32 ( IF_PC_PLUS4 [31:0] $end
$var wire 32 ) NEXT_PC [31:0] $end
$var wire 1 & RST $end
$var wire 32 * PC_PLUS4 [31:0] $end
$var wire 32 + PC [31:0] $end
$var wire 32 , IF_INSTRUCTION [31:0] $end
$scope module PC_INST $end
$var wire 1 $ CLK $end
$var wire 32 - NEXT_PC [31:0] $end
$var wire 1 & RST $end
$var wire 32 . PC_PLUS4 [31:0] $end
$var reg 32 / PC [31:0] $end
$upscope $end
$scope module instruction_memory $end
$var wire 32 0 ADDRESS [31:0] $end
$var wire 32 1 INSTRUCTION [31:0] $end
$var parameter 32 2 MEM_SIZE $end
$upscope $end
$upscope $end
$upscope $end
$enddefinitions $end
$comment Show the parameter values. $end
$dumpall
b10000000000 2
$end
#0
$dumpvars
b10011 1
b0 0
b0 /
b100 .
b0 -
b10011 ,
b0 +
b100 *
b0 )
b100 (
b0 '
1&
b0 %
0$
b0 #
b10011 "
b100 !
$end
#5
1$
#10
0$
0&
#15
1$
#20
0$
b100 %
b100 )
b100 -
#25
b1000 !
b1000 (
b1000 *
b1000 .
b10010011 "
b10010011 ,
b10010011 1
b100 #
b100 '
b100 +
b100 /
b100 0
1$
#30
0$
b1000 %
b1000 )
b1000 -
#35
b1100 !
b1100 (
b1100 *
b1100 .
b100000000000100010011 "
b100000000000100010011 ,
b100000000000100010011 1
b1000 #
b1000 '
b1000 +
b1000 /
b1000 0
1$
#40
0$
b1100 %
b1100 )
b1100 -
#45
b10000 !
b10000 (
b10000 *
b10000 .
b1000001000000110110011 "
b1000001000000110110011 ,
b1000001000000110110011 1
b1100 #
b1100 '
b1100 +
b1100 /
b1100 0
1$
#50
0$
b10000 %
b10000 )
b10000 -
#55
b10100 !
b10100 (
b10100 *
b10100 .
b1100010000000100110011 "
b1100010000000100110011 ,
b1100010000000100110011 1
b10000 #
b10000 '
b10000 +
b10000 /
b10000 0
1$
#60
0$
b10100 %
b10100 )
b10100 -
#65
b11000 !
b11000 (
b11000 *
b11000 .
b1000000010000011010000110000011 "
b1000000010000011010000110000011 ,
b1000000010000011010000110000011 1
b10100 #
b10100 '
b10100 +
b10100 /
b10100 0
1$
