BranchControlUnit/branch_control_unit.v
module BRANCH_CONTROL_UNIT(
    input wire JUMP,
    input wire BRANCH,
    input wire [2:0] FUNC3,
    input wire [31:0] OUT1,
    input wire [31:0] OUT2,
    input wire [31:0] ALU_RESULT,
    output reg [31:0] TARGET_ADDRESS,
    output reg BRANCH_SELECT
);

    always @(*) begin
        // Default values
        TARGET_ADDRESS = 32'b0;
        BRANCH_SELECT = 1'b0;

        if (JUMP) begin
            // For jump instructions, the target address is the ALU result
            TARGET_ADDRESS = ALU_RESULT;
            TARGET_ADDRESS[0] = 2'b0; // Align to 32-bit address
            BRANCH_SELECT = 1'b1;
        end else if (BRANCH) begin
            // For branch instructions, determine if the branch should be taken
            case (FUNC3)
                3'b000: begin // BEQ
                    if (OUT1 == OUT2) begin
                        TARGET_ADDRESS = ALU_RESULT;
                        BRANCH_SELECT = 1'b1;
                    end
                end
                3'b001: begin // BNE
                    if (OUT1 != OUT2) begin
                        TARGET_ADDRESS = ALU_RESULT;
                        BRANCH_SELECT = 1'b1;
                    end
                end
                3'b100: begin // BLT
                    if ($signed(OUT1) < $signed(OUT2)) begin
                        TARGET_ADDRESS = ALU_RESULT;
                        BRANCH_SELECT = 1'b1;
                    end
                end
                3'b101: begin // BGE
                    if ($signed(OUT1) >= $signed(OUT2)) begin
                        TARGET_ADDRESS = ALU_RESULT;
                        BRANCH_SELECT = 1'b1;
                    end
                end
                3'b110: begin // BLTU
                    if (OUT1 < OUT2) begin
                        TARGET_ADDRESS = ALU_RESULT;
                        BRANCH_SELECT = 1'b1;
                    end
                end
                3'b111: begin // BGEU
                    if (OUT1 >= OUT2) begin
                        TARGET_ADDRESS = ALU_RESULT;
                        BRANCH_SELECT = 1'b1;
                    end
                end
                default: begin
                    TARGET_ADDRESS = 32'b0;
                    BRANCH_SELECT = 1'b0;
                end
            endcase
        end
    end

endmodule

BranchControlUnit/branch_control_unit_tb.v
`timescale 1ns / 1ps

module branch_control_unit_tb;
    // Inputs
    reg JUMP;
    reg BRANCH;
    reg [2:0] FUNC3;
    reg [31:0] OUT1;
    reg [31:0] OUT2;
    reg [31:0] ALU_RESULT;

    // Outputs
    wire [31:0] TARGET_ADDRESS;
    wire BRANCH_SELECT;

    // Instantiate the Unit Under Test (UUT)
    branch_control_unit uut (
        .JUMP(JUMP),
        .BRANCH(BRANCH),
        .FUNC3(FUNC3),
        .OUT1(OUT1),
        .OUT2(OUT2),
        .ALU_RESULT(ALU_RESULT),
        .TARGET_ADDRESS(TARGET_ADDRESS),
        .BRANCH_SELECT(BRANCH_SELECT)
    );

    initial begin
        // Open VCD file for GTKWave
        $dumpfile("branch_control_unit_tb.vcd");
        $dumpvars(0, branch_control_unit_tb);

        // Initialize Inputs
        JUMP = 0;
        BRANCH = 0;
        FUNC3 = 3'b000;
        OUT1 = 32'b0;
        OUT2 = 32'b0;
        ALU_RESULT = 32'b0;

        // Test JUMP instruction
        #10 JUMP = 1; ALU_RESULT = 32'h00000010; #10;
        JUMP = 0;

        // Test BEQ instruction
        #10 BRANCH = 1; FUNC3 = 3'b000; OUT1 = 32'h00000001; OUT2 = 32'h00000001; ALU_RESULT = 32'h00000020; #10;
        BRANCH = 0;

        // Test BNE instruction
        #10 BRANCH = 1; FUNC3 = 3'b001; OUT1 = 32'h00000001; OUT2 = 32'h00000002; ALU_RESULT = 32'h00000030; #10;
        BRANCH = 0;

        // Test BLT instruction
        #10 BRANCH = 1; FUNC3 = 3'b100; OUT1 = 32'h00000001; OUT2 = 32'h00000002; ALU_RESULT = 32'h00000040; #10;
        BRANCH = 0;

        // Test BGE instruction
        #10 BRANCH = 1; FUNC3 = 3'b101; OUT1 = 32'h00000002; OUT2 = 32'h00000001; ALU_RESULT = 32'h00000050; #10;
        BRANCH = 0;

        // Test BLTU instruction
        #10 BRANCH = 1; FUNC3 = 3'b110; OUT1 = 32'h00000001; OUT2 = 32'h00000002; ALU_RESULT = 32'h00000060; #10;
        BRANCH = 0;

        // Test BGEU instruction
        #10 BRANCH = 1; FUNC3 = 3'b111; OUT1 = 32'h00000002; OUT2 = 32'h00000001; ALU_RESULT = 32'h00000070; #10;
        BRANCH = 0;

        // Test JAL instruction
        #10 JUMP = 1; ALU_RESULT = 32'h00000080; #10;
        JUMP = 0;

        // Finish the simulation
        $finish;
    end
      
endmodule

BranchControlUnit/branch_control_unit_tb.vcd
$date
	Tue Jan 14 15:59:05 2025
$end
$version
	Icarus Verilog
$end
$timescale
	1ps
$end
$scope module branch_control_unit_tb $end
$var wire 32 ! TARGET_ADDRESS [31:0] $end
$var wire 1 " BRANCH_SELECT $end
$var reg 32 # ALU_RESULT [31:0] $end
$var reg 1 $ BRANCH $end
$var reg 3 % FUNC3 [2:0] $end
$var reg 1 & JUMP $end
$var reg 32 ' OUT1 [31:0] $end
$var reg 32 ( OUT2 [31:0] $end
$scope module uut $end
$var wire 32 ) ALU_RESULT [31:0] $end
$var wire 1 $ BRANCH $end
$var wire 3 * FUNC3 [2:0] $end
$var wire 1 & JUMP $end
$var wire 32 + OUT1 [31:0] $end
$var wire 32 , OUT2 [31:0] $end
$var reg 1 " BRANCH_SELECT $end
$var reg 32 - TARGET_ADDRESS [31:0] $end
$upscope $end
$upscope $end
$enddefinitions $end
$comment Show the parameter values. $end
$dumpall
$end
#0
$dumpvars
b0 -
b0 ,
b0 +
b0 *
b0 )
b0 (
b0 '
0&
b0 %
0$
b0 #
0"
b0 !
$end
#10000
1"
b10000 !
b10000 -
b10000 #
b10000 )
1&
#20000
0"
b0 !
b0 -
0&
#30000
1"
b100000 !
b100000 -
b100000 #
b100000 )
b1 (
b1 ,
b1 '
b1 +
1$
#40000
0"
b0 !
b0 -
0$
#50000
1"
b110000 !
b110000 -
b110000 #
b110000 )
b10 (
b10 ,
b1 %
b1 *
1$
#60000
0"
b0 !
b0 -
0$
#70000
1"
b1000000 !
b1000000 -
b1000000 #
b1000000 )
b100 %
b100 *
1$
#80000
0"
b0 !
b0 -
0$
#90000
1"
b1010000 !
b1010000 -
b1010000 #
b1010000 )
b1 (
b1 ,
b10 '
b10 +
b101 %
b101 *
1$
#100000
0"
b0 !
b0 -
0$
#110000
1"
b1100000 !
b1100000 -
b1100000 #
b1100000 )
b10 (
b10 ,
b1 '
b1 +
b110 %
b110 *
1$
#120000
0"
b0 !
b0 -
0$
#130000
1"
b1110000 !
b1110000 -
b1110000 #
b1110000 )
b1 (
b1 ,
b10 '
b10 +
b111 %
b111 *
1$
#140000
0"
b0 !
b0 -
0$
#150000
1"
b10000000 !
b10000000 -
b10000000 #
b10000000 )
1&
#160000
0"
b0 !
b0 -
0&
