ControlUnit/control_unit.v

module control_unit(OPCODE, FUNC3, FUNC7, WRITE_EN, MEM_WRITE, MEM_READ, BRANCH, JUMP, PC_SELECT, IMM_SELECT, JAL_SELECT, DATA_MEM_SELECT, WB_METHOD, IMM_PICK);
    input [6:0] OPCODE, FUNC7;
    input [2:0] FUNC3;
    output reg WRITE_EN, MEM_WRITE, MEM_READ, BRANCH, JUMP, PC_SELECT, IMM_SELECT, JAL_SELECT, DATA_MEM_SELECT;
    output reg [1:0] WB_METHOD;
    output reg [2:0] IMM_PICK;

    // always block * to run the block whenever any input changes  
    always @(*)
    begin
        // Default values
        WRITE_EN = 1'b0;
        MEM_WRITE = 1'b0;
        MEM_READ = 1'b0;
        BRANCH = 1'b0;
        JUMP = 1'b0;
        PC_SELECT = 1'b0;
        IMM_SELECT = 1'b0;
        JAL_SELECT = 1'b0;
        DATA_MEM_SELECT = 1'b0;
        WB_METHOD = 2'b00;
        IMM_PICK = 3'b000;

        case (OPCODE)

        //////////////////////////////////////////////////// R-type //////////////////////////////////////////////////////////////////
        8'b0110011: 
            begin
                WRITE_EN = 1'b1;
            end

        //////////////////////////////////////////////////// I-type //////////////////////////////////////////////////////////////////
        8'b0000011: 
            if (FUNC3 == 3'b000 || // LB
                FUNC3 == 3'b001 || // LH
                FUNC3 == 3'b010 || // LW
                FUNC3 == 3'b100 || // LBU
                FUNC3 == 3'b101)    // LHU
                begin
                    IMM_SELECT = 1'b1;
                    WRITE_EN = 1'b1;
                    MEM_READ = 1'b1;
                end
        8'b1100111: 
            case (FUNC3)
            3'b000: // JALR
            begin
                WRITE_EN = 1'b1;
                JAL_SELECT = 1'b1;
                IMM_SELECT = 1'b1;
                JUMP = 1'b1;
                // Set the LSB of the calculated address to 0 to ensure it is word-aligned.
            end
            endcase
        8'b0010011:
            if (FUNC3 == 3'b000 || // ADDI
                FUNC3 == 3'b010 || // SLTI
                FUNC3 == 3'b011 || // SLTIU
                FUNC3 == 3'b100 || // XORI
                FUNC3 == 3'b110 || // ORI
                FUNC3 == 3'b111)   // ANDI
            begin
                WRITE_EN = 1'b1;
                IMM_SELECT = 1'b1;
            end
            
            else if ((FUNC7 == 7'b0000000 && FUNC3 == 3'b001) || // SLLI
                (FUNC7 == 7'b0000000 && FUNC3 == 3'b101) || // SRLI
                (FUNC7 == 7'b0100000 && FUNC3 == 3'b101))   // SRAI
            begin
                WRITE_EN = 1'b1;
                IMM_SELECT = 1'b1;
            end

        //////////////////////////////////////////////////// S-type //////////////////////////////////////////////////////////////////
        8'b0100011: 
            case (FUNC3)
            3'b000: // SB
            begin
                MEM_WRITE = 1'b1;
                IMM_SELECT = 1'b1;
                WB_METHOD = 2'b00;
                IMM_PICK = 3'b001;
            end
            3'b001: // SH
            begin
                MEM_WRITE = 1'b1;
                IMM_SELECT = 1'b1;
                WB_METHOD = 2'b01;
                IMM_PICK = 3'b001;
            end
            3'b010: // SW
            begin
                MEM_WRITE = 1'b1;
                IMM_SELECT = 1'b1;
                WB_METHOD = 2'b10;
                IMM_PICK = 3'b001;
            end
            endcase

        //////////////////////////////////////////////////// U-type //////////////////////////////////////////////////////////////////
        8'b0110111: // LUI
            begin
            WRITE_EN = 1'b1;
            IMM_PICK = 3'b010;
            IMM_SELECT = 1'b1;
            end
        8'b0010111: // AUIPC
            begin
            WRITE_EN = 1'b1;
            IMM_PICK = 3'b010;
            IMM_SELECT = 1'b1;
            PC_SELECT = 1'b1;
            end

        //////////////////////////////////////////////////// B-type //////////////////////////////////////////////////////////////////
        8'b1100011: 
            if (FUNC3 == 3'b000 || // BEQ
                FUNC3 == 3'b001 || // BNE
                FUNC3 == 3'b100 || // BLT
                FUNC3 == 3'b101 || // BGE
                FUNC3 == 3'b110 || // BLTU
                FUNC3 == 3'b111)   // BGEU
            begin
                BRANCH = 1'b1;
                PC_SELECT = 1'b1;
                IMM_SELECT = 1'b1;
                IMM_PICK = 3'b011;
            end


        //////////////////////////////////////////////////// J-type //////////////////////////////////////////////////////////////////
        8'b1101111: // JAL
            begin
            JUMP = 1'b1;
            JAL_SELECT = 1'b1;
            PC_SELECT = 1'b1;
            IMM_SELECT = 1'b1;
            IMM_PICK = 3'b100;
            WRITE_EN = 1'b1;
            end
        endcase


    end 

endmodule

ControlUnit/control_unit_tb.v
`timescale 1ns / 1ps

module control_unit_tb;
    // Inputs
    reg [6:0] OPCODE;
    reg [2:0] FUNC3;
    reg [6:0] FUNC7;

    // Outputs
    wire WRITE_EN;
    wire MEM_WRITE;
    wire MEM_READ;
    wire BRANCH;
    wire JUMP;
    wire PC_SELECT;
    wire IMM_SELECT;
    wire JAL_SELECT;
    wire DATA_MEM_SELECT;
    wire [1:0] WB_METHOD;
    wire [2:0] IMM_PICK;

    // Instantiate the Unit Under Test (UUT)
    control_unit uut (
        .OPCODE(OPCODE), 
        .FUNC3(FUNC3), 
        .FUNC7(FUNC7), 
        .WRITE_EN(WRITE_EN), 
        .MEM_WRITE(MEM_WRITE), 
        .MEM_READ(MEM_READ), 
        .BRANCH(BRANCH), 
        .JUMP(JUMP), 
        .PC_SELECT(PC_SELECT), 
        .IMM_SELECT(IMM_SELECT), 
        .JAL_SELECT(JAL_SELECT), 
        .DATA_MEM_SELECT(DATA_MEM_SELECT), 
        .WB_METHOD(WB_METHOD), 
        .IMM_PICK(IMM_PICK)
    );

    initial begin
        // Initialize Inputs
        OPCODE = 0;
        FUNC3 = 0;
        FUNC7 = 0;

        // Open VCD file for GTKWave
        $dumpfile("control_unit_tb.vcd");
        $dumpvars(0, control_unit_tb);

        // Wait 100 ns for global reset to finish
        #10;
        
        // Test R-type instructions
        OPCODE = 8'b0110011;
        FUNC3 = 3'b000; FUNC7 = 7'b0000000; #10; // ADD
        FUNC3 = 3'b000; FUNC7 = 7'b0100000; #10; // SUB
        FUNC3 = 3'b001; FUNC7 = 7'b0000000; #10; // SLL
        FUNC3 = 3'b010; FUNC7 = 7'b0000000; #10; // SLT
        FUNC3 = 3'b011; FUNC7 = 7'b0000000; #10; // SLTU
        FUNC3 = 3'b100; FUNC7 = 7'b0000000; #10; // XOR
        FUNC3 = 3'b101; FUNC7 = 7'b0000000; #10; // SRL
        FUNC3 = 3'b101; FUNC7 = 7'b0100000; #10; // SRA
        FUNC3 = 3'b110; FUNC7 = 7'b0000000; #10; // OR
        FUNC3 = 3'b111; FUNC7 = 7'b0000000; #10; // AND

        // Test I-type instructions
        OPCODE = 8'b0000011;
        FUNC3 = 3'b000; #10; // LB
        FUNC3 = 3'b001; #10; // LH
        FUNC3 = 3'b010; #10; // LW
        FUNC3 = 3'b100; #10; // LBU
        FUNC3 = 3'b101; #10; // LHU

        OPCODE = 8'b1100111;
        FUNC3 = 3'b000; #10; // JALR

        OPCODE = 8'b0010011;
        FUNC3 = 3'b000; #10; // ADDI
        FUNC3 = 3'b010; #10; // SLTI
        FUNC3 = 3'b011; #10; // SLTIU
        FUNC3 = 3'b100; #10; // XORI
        FUNC3 = 3'b110; #10; // ORI
        FUNC3 = 3'b111; #10; // ANDI
        FUNC3 = 3'b001; FUNC7 = 7'b0000000; #10; // SLLI
        FUNC3 = 3'b101; FUNC7 = 7'b0000000; #10; // SRLI
        FUNC3 = 3'b101; FUNC7 = 7'b0100000; #10; // SRAI

        // Test S-type instructions
        OPCODE = 8'b0100011;
        FUNC3 = 3'b000; #10; // SB
        FUNC3 = 3'b001; #10; // SH
        FUNC3 = 3'b010; #10; // SW

        // Test U-type instructions
        OPCODE = 8'b0110111; #10; // LUI
        OPCODE = 8'b0010111; #10; // AUIPC

        // Test B-type instructions
        OPCODE = 8'b1100011;
        FUNC3 = 3'b000; #10; // BEQ
        FUNC3 = 3'b001; #10; // BNE
        FUNC3 = 3'b100; #10; // BLT
        FUNC3 = 3'b101; #10; // BGE
        FUNC3 = 3'b110; #10; // BLTU
        FUNC3 = 3'b111; #10; // BGEU

        // Test J-type instruction
        OPCODE = 8'b1101111; #10; // JAL


        OPCODE = 8'b0010011;
        FUNC3 = 3'b000; #10; // NOP when rd -> x0 ; rs1 -> x0 ; imm -> 0
        $finish; // $stop; only pauses the simulation
    end
      
endmodule

ControlUnit/control_unit_tb.vcd
$date
	Sun Jan 05 11:43:16 2025
$end
$version
	Icarus Verilog
$end
$timescale
	1ps
$end
$scope module control_unit_tb $end
$var wire 1 ! WRITE_EN $end
$var wire 2 " WB_METHOD [1:0] $end
$var wire 1 # PC_SELECT $end
$var wire 1 $ MEM_WRITE $end
$var wire 1 % MEM_READ $end
$var wire 1 & JUMP $end
$var wire 1 ' JAL_SELECT $end
$var wire 1 ( IMM_SELECT $end
$var wire 3 ) IMM_PICK [2:0] $end
$var wire 1 * DATA_MEM_SELECT $end
$var wire 1 + BRANCH $end
$var reg 3 , FUNC3 [2:0] $end
$var reg 7 - FUNC7 [6:0] $end
$var reg 7 . OPCODE [6:0] $end
$scope module uut $end
$var wire 3 / FUNC3 [2:0] $end
$var wire 7 0 FUNC7 [6:0] $end
$var wire 7 1 OPCODE [6:0] $end
$var reg 1 + BRANCH $end
$var reg 1 * DATA_MEM_SELECT $end
$var reg 3 2 IMM_PICK [2:0] $end
$var reg 1 ( IMM_SELECT $end
$var reg 1 ' JAL_SELECT $end
$var reg 1 & JUMP $end
$var reg 1 % MEM_READ $end
$var reg 1 $ MEM_WRITE $end
$var reg 1 # PC_SELECT $end
$var reg 2 3 WB_METHOD [1:0] $end
$var reg 1 ! WRITE_EN $end
$upscope $end
$upscope $end
$enddefinitions $end
$comment Show the parameter values. $end
$dumpall
$end
#0
$dumpvars
b0 3
b0 2
b0 1
b0 0
b0 /
b0 .
b0 -
b0 ,
0+
0*
b0 )
0(
0'
0&
0%
0$
0#
b0 "
0!
$end
#10000
1!
b110011 .
b110011 1
#20000
1!
b100000 -
b100000 0
#30000
1!
b0 -
b0 0
b1 ,
b1 /
#40000
1!
b10 ,
b10 /
#50000
1!
b11 ,
b11 /
#60000
1!
b100 ,
b100 /
#70000
1!
b101 ,
b101 /
#80000
1!
b100000 -
b100000 0
#90000
1!
b0 -
b0 0
b110 ,
b110 /
#100000
1!
b111 ,
b111 /
#110000
1%
1(
1!
b0 ,
b0 /
b11 .
b11 1
#120000
1(
1%
1!
b1 ,
b1 /
#130000
1(
1%
1!
b10 ,
b10 /
#140000
1(
1%
1!
b100 ,
b100 /
#150000
1(
1%
1!
b101 ,
b101 /
#160000
1&
1'
1(
0%
1!
b0 ,
b0 /
b1100111 .
b1100111 1
#170000
0'
1(
0&
1!
b10011 .
b10011 1
#180000
1(
1!
b10 ,
b10 /
#190000
1(
1!
b11 ,
b11 /
#200000
1(
1!
b100 ,
b100 /
#210000
1(
1!
b110 ,
b110 /
#220000
1(
1!
b111 ,
b111 /
#230000
1(
1!
b1 ,
b1 /
#240000
1(
1!
b101 ,
b101 /
#250000
1(
1!
b100000 -
b100000 0
#260000
b1 )
b1 2
1$
1(
0!
b0 ,
b0 /
b100011 .
b100011 1
#270000
b1 "
b1 3
b1 )
b1 2
1(
1$
b1 ,
b1 /
#280000
b1 )
b1 2
b10 "
b10 3
1(
1$
b10 ,
b10 /
#290000
1!
b10 )
b10 2
b0 "
b0 3
1(
0$
b110111 .
b110111 1
#300000
1#
b10 )
b10 2
1(
1!
b10111 .
b10111 1
#310000
1+
b11 )
b11 2
1(
1#
0!
b0 ,
b0 /
b1100011 .
b1100011 1
#320000
b11 )
b11 2
1(
1#
1+
b1 ,
b1 /
#330000
b11 )
b11 2
1(
1#
1+
b100 ,
b100 /
#340000
b11 )
b11 2
1(
1#
1+
b101 ,
b101 /
#350000
b11 )
b11 2
1(
1#
1+
b110 ,
b110 /
#360000
b11 )
b11 2
1(
1#
1+
b111 ,
b111 /
#370000
1!
1'
1&
b100 )
b100 2
1(
1#
0+
b1101111 .
b1101111 1
#380000
b0 )
b0 2
0'
1(
0#
0&
1!
b0 ,
b0 /
b10011 .
b10011 1
