ImmidiatePick/imm_pick.v
module imm_pick(
    input [31:0] INSTRUCTION,
    input [2:0] IMM_PICK,
    output reg [31:0] IMMIDIATE
);

always @(*) begin
    case (IMM_PICK)
        3'b000: // I-type
            IMMIDIATE = {{20{INSTRUCTION[31]}}, INSTRUCTION[31:20]};
        3'b001: // S-type
            IMMIDIATE = {{20{INSTRUCTION[31]}}, INSTRUCTION[31:25], INSTRUCTION[11:7]};
        3'b010: // U-type
            IMMIDIATE = {INSTRUCTION[31:12], 12'b0};
        3'b011: // B-type
            IMMIDIATE = {{19{INSTRUCTION[31]}}, INSTRUCTION[31], INSTRUCTION[7], INSTRUCTION[30:25], INSTRUCTION[11:8], 1'b0};
        3'b100: // J-type
            IMMIDIATE = {{11{INSTRUCTION[31]}}, INSTRUCTION[31], INSTRUCTION[19:12], INSTRUCTION[20], INSTRUCTION[30:21], 1'b0};
        default:// Default case
            IMMIDIATE = 32'b0;
    endcase
end

endmodule

ImmidiatePick/imm_pick_tb.v
`timescale 1ns / 1ps

module imm_pick_tb;
    // Inputs
    reg [31:0] INSTRUCTION;
    reg [2:0] IMM_PICK;

    // Outputs
    wire [31:0] IMMIDIATE;

    // Instantiate the Unit Under Test (UUT)
    imm_pick uut (
        .INSTRUCTION(INSTRUCTION), 
        .IMM_PICK(IMM_PICK), 
        .IMMIDIATE(IMMIDIATE)
    );

    initial begin
        // Open VCD file for GTKWave
        $dumpfile("imm_pick_tb.vcd");
        $dumpvars(0, imm_pick_tb);

        // Initialize Inputs
        INSTRUCTION = 32'b0;
        IMM_PICK = 3'b0;

        // Wait 100 ns for global reset to finish
        #10;

        // Test I-type IMMIDIATE 1
        INSTRUCTION = 32'b11111111111100000000000000000000; // (result - 11111111111111111111111111111111)
        IMM_PICK = 3'b000;
        #10;

        // Test I-type IMMIDIATE 2
        INSTRUCTION = 32'b00000000000011111111111111111111; // (result - 00000000000000000000000000000000)
        IMM_PICK = 3'b000;
        #10;

        // Test S-type IMMIDIATE 1
        INSTRUCTION = 32'b11111110000000000000111110000000; // (result - 11111111111111111111111111111111)
        IMM_PICK = 3'b001;
        #10;

        // Test S-type IMMIDIATE 2
        INSTRUCTION = 32'b00000001111111111111000001111111; // (result - 00000000000000000000000000000000)
        IMM_PICK = 3'b001;
        #10;

        // Test U-type IMMIDIATE 1
        INSTRUCTION = 32'b11111111111111111111000000000000; // (result - 11111111111111111111000000000000)
        IMM_PICK = 3'b010;
        #10;

        // Test U-type IMMIDIATE 2
        INSTRUCTION = 32'b00000000000000000000111111111111; // (result - 00000000000000000000000000000000)
        IMM_PICK = 3'b010;
        #10;

        // Test B-type IMMIDIATE
        INSTRUCTION = 32'b11111110000000000000111110000000; // (result - 11111111111111111111111111111110)
        IMM_PICK = 3'b011;
        #10;

        // Test B-type IMMIDIATE
        INSTRUCTION = 32'b00000001111111111111000001111111; // (result - 00000000000000000000000000000000)
        IMM_PICK = 3'b011;
        #10;

        // Test J-type IMMIDIATE
        INSTRUCTION = 32'h87654321; // Example INSTRUCTION
        IMM_PICK = 3'b100;
        #10;

        // Add more test cases as needed

        $finish;
    end
      
endmodule

ImmidiatePick/imm_pick_tb.vcd
$date
	Tue Jan 14 13:23:24 2025
$end
$version
	Icarus Verilog
$end
$timescale
	1ps
$end
$scope module imm_pick_tb $end
$var wire 32 ! IMMIDIATE [31:0] $end
$var reg 3 " IMM_PICK [2:0] $end
$var reg 32 # INSTRUCTION [31:0] $end
$scope module uut $end
$var wire 3 $ IMM_PICK [2:0] $end
$var wire 32 % INSTRUCTION [31:0] $end
$var reg 32 & IMMIDIATE [31:0] $end
$upscope $end
$upscope $end
$enddefinitions $end
$comment Show the parameter values. $end
$dumpall
$end
#0
$dumpvars
b0 &
b0 %
b0 $
b0 #
b0 "
b0 !
$end
#10000
b11111111111111111111111111111111 !
b11111111111111111111111111111111 &
b11111111111100000000000000000000 #
b11111111111100000000000000000000 %
#20000
b0 !
b0 &
b11111111111111111111 #
b11111111111111111111 %
#30000
b11111111111111111111111111111111 !
b11111111111111111111111111111111 &
b1 "
b1 $
b11111110000000000000111110000000 #
b11111110000000000000111110000000 %
#40000
b0 !
b0 &
b1111111111111000001111111 #
b1111111111111000001111111 %
#50000
b11111111111111111111000000000000 !
b11111111111111111111000000000000 &
b10 "
b10 $
b11111111111111111111000000000000 #
b11111111111111111111000000000000 %
#60000
b0 !
b0 &
b111111111111 #
b111111111111 %
#70000
b11111111111111111111111111111110 !
b11111111111111111111111111111110 &
b11 "
b11 $
b11111110000000000000111110000000 #
b11111110000000000000111110000000 %
#80000
b0 !
b0 &
b1111111111111000001111111 #
b1111111111111000001111111 %
#90000
b11111111111101010100000001110110 !
b11111111111101010100000001110110 &
b100 "
b100 $
b10000111011001010100001100100001 #
b10000111011001010100001100100001 %
