Mux/mux.v
module MUX (
    input wire [31:0] IN0,
    input wire [31:0] IN1,
    input wire SEL,
    output wire [31:0] OUT
);

    assign OUT = SEL ? IN1 : IN0;

endmodule

LoadProcessingUnit/load_processing_unit.v
module LOAD_PROCESSING_UNIT(
    input wire [2:0] FUNC3,
    input wire [31:0] DATA_OUT,
    output reg [31:0] PROCESSED_DATA_OUT
);

    always @(*) begin
        case (FUNC3)
            3'b000: // LB (Load Byte)
                PROCESSED_DATA_OUT = {{24{DATA_OUT[7]}}, DATA_OUT[7:0]};
            3'b001: // LH (Load Halfword)
                PROCESSED_DATA_OUT = {{16{DATA_OUT[15]}}, DATA_OUT[15:0]};
            3'b010: // LW (Load Word)
                PROCESSED_DATA_OUT = DATA_OUT;
            3'b100: // LBU (Load Byte Unsigned)
                PROCESSED_DATA_OUT = {24'b0, DATA_OUT[7:0]};
            3'b101: // LHU (Load Halfword Unsigned)
                PROCESSED_DATA_OUT = {16'b0, DATA_OUT[15:0]};
            default: // Default case
                PROCESSED_DATA_OUT = 32'b0;
        endcase
    end

endmodule

CPU/WB/WB.v
module WB (
    input wire CLK,
    input wire RST,
    input wire [2:0] MEM_FUNC3,
    input wire MEM_WRITE_ENABLE,
    input wire MEM_DATA_MEM_SELECT,
    input wire [31:0] MEM_JAL_SELECTED,
    input wire [31:0] MEM_DATA_OUT,
    input wire [4:0] MEM_RD,

    output wire WB_WRITE_ENABLE,
    output wire [31:0] WB_WRITE_DATA,
    output wire [4:0] WB_RD
);

    wire [31:0] PROCESSED_DATA_OUT;

    // Load Processing Unit
    LOAD_PROCESSING_UNIT load_processing_unit (
        .FUNC3(MEM_FUNC3),
        .DATA_OUT(MEM_DATA_OUT),
        .PROCESSED_DATA_OUT(PROCESSED_DATA_OUT)
    );

    // MUX
    MUX data_mem_select (
        .IN0(MEM_JAL_SELECTED),
        .IN1(PROCESSED_DATA_OUT),
        .SEL(MEM_DATA_MEM_SELECT),
        .OUT(WB_WRITE_DATA)
    );

    // Output assignments
    assign WB_WRITE_ENABLE = MEM_WRITE_ENABLE;
    assign WB_RD = MEM_RD;

endmodule

CPU/WB/WB_tb.v
`timescale 1ns / 1ps

module WB_tb;
    // Inputs
    reg CLK;
    reg RST;
    reg [2:0] MEM_FUNC3;
    reg MEM_WRITE_ENABLE;
    reg MEM_DATA_MEM_SELECT;
    reg [31:0] MEM_JAL_SELECTED;
    reg [31:0] MEM_DATA_OUT;
    reg [4:0] MEM_RD;

    // Outputs
    wire WB_WRITE_ENABLE;
    wire [31:0] WB_WRITE_DATA;
    wire [4:0] WB_RD;

    // Instantiate the Unit Under Test (UUT)
    WB uut (
        .CLK(CLK),
        .RST(RST),
        .MEM_FUNC3(MEM_FUNC3),
        .MEM_WRITE_ENABLE(MEM_WRITE_ENABLE),
        .MEM_DATA_MEM_SELECT(MEM_DATA_MEM_SELECT),
        .MEM_JAL_SELECTED(MEM_JAL_SELECTED),
        .MEM_DATA_OUT(MEM_DATA_OUT),
        .MEM_RD(MEM_RD),
        .WB_WRITE_ENABLE(WB_WRITE_ENABLE),
        .WB_WRITE_DATA(WB_WRITE_DATA),
        .WB_RD(WB_RD)
    );

    initial begin
        // Initialize Inputs
        CLK = 0;
        RST = 1;
        MEM_FUNC3 = 0;
        MEM_WRITE_ENABLE = 0;
        MEM_DATA_MEM_SELECT = 0;
        MEM_JAL_SELECTED = 0;
        MEM_DATA_OUT = 0;
        MEM_RD = 0;

        // Wait for global reset
        #10;
        RST = 0;

        // Test case 1: Write enable with data memory select (LW)
        MEM_FUNC3 = 3'b010; // LW
        MEM_WRITE_ENABLE = 1;
        MEM_DATA_MEM_SELECT = 1;
        MEM_JAL_SELECTED = 32'h00000004;
        MEM_DATA_OUT = 32'hDEADBEEF;
        MEM_RD = 5'b00001;
        #10;

        // Test case 2: Write enable with JAL selected
        MEM_DATA_MEM_SELECT = 0;
        MEM_JAL_SELECTED = 32'hCAFEBABE;
        #10;

        // Test case 3: Write disable
        MEM_WRITE_ENABLE = 0;
        #10;

        // Test case 4: Load Byte (LB)
        MEM_FUNC3 = 3'b000; // LB
        MEM_WRITE_ENABLE = 1;
        MEM_DATA_MEM_SELECT = 1;
        MEM_DATA_OUT = 32'h000A00FA;
        MEM_RD = 5'b00010;
        #10;

        // Test case 5: Load Halfword (LH)
        MEM_FUNC3 = 3'b001; // LH
        MEM_WRITE_ENABLE = 1;
        MEM_DATA_MEM_SELECT = 1;
        MEM_DATA_OUT = 32'h0F00FAFF;
        MEM_RD = 5'b00011;
        #10;

        // Test case 6: Load Byte Unsigned (LBU)
        MEM_FUNC3 = 3'b100; // LBU
        MEM_WRITE_ENABLE = 1;
        MEM_DATA_MEM_SELECT = 1;
        MEM_DATA_OUT = 32'h000000FF;
        MEM_RD = 5'b00100;
        #10;

        // Test case 7: Load Halfword Unsigned (LHU)
        MEM_FUNC3 = 3'b101; // LHU
        MEM_WRITE_ENABLE = 1;
        MEM_DATA_MEM_SELECT = 1;
        MEM_DATA_OUT = 32'h0000FFFF;
        MEM_RD = 5'b00101;
        #10;

        // Finish simulation
        $finish;
    end

    // Clock generation
    always #5 CLK = ~CLK;

    // Dump waveform
    initial begin
        $dumpfile("WB_tb.vcd");
        $dumpvars(0, WB_tb);
    end

endmodule

// command to run simulation
// iverilog -o WB_tb.vvp WB_tb.v WB.v ../../LoadProcessingUnit/LOAD_PROCESSING_UNIT.v ../../MUX/MUX.v
// vvp WB_tb.vvp
// gtkwave WB_tb.vcd

CPU/WB/WB_tb.vcd
$date
	Sun Jan 26 13:08:22 2025
$end
$version
	Icarus Verilog
$end
$timescale
	1ps
$end
$scope module WB_tb $end
$var wire 1 ! WB_WRITE_ENABLE $end
$var wire 32 " WB_WRITE_DATA [31:0] $end
$var wire 5 # WB_RD [4:0] $end
$var reg 1 $ CLK $end
$var reg 1 % MEM_DATA_MEM_SELECT $end
$var reg 32 & MEM_DATA_OUT [31:0] $end
$var reg 3 ' MEM_FUNC3 [2:0] $end
$var reg 32 ( MEM_JAL_SELECTED [31:0] $end
$var reg 5 ) MEM_RD [4:0] $end
$var reg 1 * MEM_WRITE_ENABLE $end
$var reg 1 + RST $end
$scope module uut $end
$var wire 1 $ CLK $end
$var wire 1 % MEM_DATA_MEM_SELECT $end
$var wire 32 , MEM_DATA_OUT [31:0] $end
$var wire 3 - MEM_FUNC3 [2:0] $end
$var wire 32 . MEM_JAL_SELECTED [31:0] $end
$var wire 5 / MEM_RD [4:0] $end
$var wire 1 * MEM_WRITE_ENABLE $end
$var wire 1 + RST $end
$var wire 5 0 WB_RD [4:0] $end
$var wire 1 ! WB_WRITE_ENABLE $end
$var wire 32 1 WB_WRITE_DATA [31:0] $end
$var wire 32 2 PROCESSED_DATA_OUT [31:0] $end
$scope module data_mem_select $end
$var wire 32 3 IN0 [31:0] $end
$var wire 1 % SEL $end
$var wire 32 4 OUT [31:0] $end
$var wire 32 5 IN1 [31:0] $end
$upscope $end
$scope module load_processing_unit $end
$var wire 32 6 DATA_OUT [31:0] $end
$var wire 3 7 FUNC3 [2:0] $end
$var reg 32 8 PROCESSED_DATA_OUT [31:0] $end
$upscope $end
$upscope $end
$upscope $end
$enddefinitions $end
$comment Show the parameter values. $end
$dumpall
$end
#0
$dumpvars
b0 8
b0 7
b0 6
b0 5
b0 4
b0 3
b0 2
b0 1
b0 0
b0 /
b0 .
b0 -
b0 ,
1+
0*
b0 )
b0 (
b0 '
b0 &
0%
0$
b0 #
b0 "
0!
$end
#5000
1$
#10000
b11011110101011011011111011101111 "
b11011110101011011011111011101111 1
b11011110101011011011111011101111 4
b11011110101011011011111011101111 2
b11011110101011011011111011101111 5
b11011110101011011011111011101111 8
0$
b1 #
b1 0
b1 )
b1 /
b11011110101011011011111011101111 &
b11011110101011011011111011101111 ,
b11011110101011011011111011101111 6
b100 (
b100 .
b100 3
1%
1!
1*
b10 '
b10 -
b10 7
0+
#15000
1$
#20000
b11001010111111101011101010111110 "
b11001010111111101011101010111110 1
b11001010111111101011101010111110 4
0$
b11001010111111101011101010111110 (
b11001010111111101011101010111110 .
b11001010111111101011101010111110 3
0%
#25000
1$
#30000
0$
0!
0*
#35000
1$
#40000
b11111111111111111111111111111010 "
b11111111111111111111111111111010 1
b11111111111111111111111111111010 4
b11111111111111111111111111111010 2
b11111111111111111111111111111010 5
b11111111111111111111111111111010 8
0$
b10 #
b10 0
b10 )
b10 /
b10100000000011111010 &
b10100000000011111010 ,
b10100000000011111010 6
1%
1!
1*
b0 '
b0 -
b0 7
#45000
1$
#50000
b11111111111111111111101011111111 "
b11111111111111111111101011111111 1
b11111111111111111111101011111111 4
b11111111111111111111101011111111 2
b11111111111111111111101011111111 5
b11111111111111111111101011111111 8
0$
b11 #
b11 0
b11 )
b11 /
b1111000000001111101011111111 &
b1111000000001111101011111111 ,
b1111000000001111101011111111 6
b1 '
b1 -
b1 7
#55000
1$
#60000
b11111111 "
b11111111 1
b11111111 4
b11111111 2
b11111111 5
b11111111 8
0$
b100 #
b100 0
b100 )
b100 /
b11111111 &
b11111111 ,
b11111111 6
b100 '
b100 -
b100 7
#65000
1$
#70000
b1111111111111111 "
b1111111111111111 1
b1111111111111111 4
b1111111111111111 2
b1111111111111111 5
b1111111111111111 8
0$
b101 #
b101 0
b101 )
b101 /
b1111111111111111 &
b1111111111111111 ,
b1111111111111111 6
b101 '
b101 -
b101 7
